dynamodb_timeseries/__init__.py
dynamodb_timeseries/dynamodb.py
dynamodb_timeseries/exceptions.py
dynamodb_timeseries/tableresolver.py
dynamodb_timeseries/timeseries.py
python_dynamodb_timeseries-0.2.2.dist-info/METADATA
python_dynamodb_timeseries-0.2.2.dist-info/WHEEL
python_dynamodb_timeseries-0.2.2.dist-info/top_level.txt
python_dynamodb_timeseries-0.2.2.dist-info/RECORD
