Metadata-Version: 2.1
Name: python-dynamodb-timeseries
Version: 0.2.2
Summary: Library for working with timeseries data on dynamodb
Home-page: https://github.com/sotaog/python-dynamodb-timeseries
Author: Zachary Fox
Author-email: zachreligious@gmail.com
License: MIT
Platform: UNKNOWN
Classifier: License :: OSI Approved :: MIT License
Classifier: Programming Language :: Python :: 3
Classifier: Programming Language :: Python :: 3.6
Classifier: Programming Language :: Python :: 3.7
Classifier: Programming Language :: Python :: 3.8
Requires-Dist: boto3
Requires-Dist: python-dateutil
